ioclib/injector/__init__.py
ioclib/injector/injector.py
ioclib/tests/test_container.py
ioclib_injector-1.6.dist-info/METADATA
ioclib_injector-1.6.dist-info/WHEEL
ioclib_injector-1.6.dist-info/top_level.txt
ioclib_injector-1.6.dist-info/RECORD
