Metadata-Version: 2.1
Name: ioclib-injector
Version: 1.6
Summary: UNKNOWN
Home-page: UNKNOWN
Author: UNKNOWN
Author-email: UNKNOWN
License: UNKNOWN
Platform: UNKNOWN
Requires-Dist: typing-extensions (>=4)
